eegpp/__init__.py
eegpp/__main__.py
eegpp/cnn_model_2c_Wout.py
eegpp/data_loader.py
eegpp/dataset.py
eegpp/dev.py
eegpp/evals.py
eegpp/filter_figs.py
eegpp/get_model.py
eegpp/header_lb.py
eegpp/inference.py
eegpp/model_1.pkl
eegpp/overwrite_template.py
eegpp/params.py
eegpp/post_processing.py
eegpp/train.py
eegpp/train_all_data.py
eegpp/utils.py
eegpp/visualization2.py
eegpp/misc/__init__.py
eegpp/misc/cnn_model.py
eegpp/misc/cnn_model_2d.py
eegpp/misc/cnn_model_3c.py
eegpp/misc/cnn_model_3c_3out.py
eegpp/misc/db.py
eegpp/misc/db_info.py
eegpp/misc/fft_model.py
eegpp/misc/gen_script.py
eegpp/misc/main.py
eegpp/misc/plot_re_channels.py
eegpp/misc/train_backup.py
eegpp/misc/transformer_model.py
eegpp/misc/visualization.py
eegpp/misc/xshap.py
eegpp/misc/xshap_all.py
eegpp/my_logger/__init__.py
eegpp/my_logger/logger2.py
eegpp-2.1.2.dist-info/LICENSE
eegpp-2.1.2.dist-info/METADATA
eegpp-2.1.2.dist-info/WHEEL
eegpp-2.1.2.dist-info/top_level.txt
eegpp-2.1.2.dist-info/RECORD
